{
  "summary": {
    "totalTests": 9,
    "passed": 9,
    "failed": 0,
    "unstable": 0,
    "overallStatus": "PASS",
    "timestamp": "2025-07-08T22:25:03.718Z",
    "totalDuration": 39.68185687500028,
    "averageDuration": 4.4090952083333645,
    "score": 98,
    "reliability": "LOW",
    "runsPerTest": 10
  },
  "results": [
    {
      "name": "Large HTML content processing",
      "averageTime": 4.247451750000039,
      "minTime": 2.8196560000001227,
      "maxTime": 6.404590000000098,
      "standardDeviation": 1.2382591780351195,
      "coefficient": 29.152989861158712,
      "threshold": 100,
      "status": "PASS",
      "category": "processing",
      "description": "Processing large HTML content should be fast",
      "dataSize": "8.1KB",
      "details": "Processing 8.1KB of HTML content with 400 HTML tags",
      "score": 4,
      "reliability": "LOW",
      "runs": [
        {
          "runNumber": 1,
          "processingTime": 24.435257000000092,
          "timestamp": "2025-07-08T22:25:02.297Z"
        },
        {
          "runNumber": 2,
          "processingTime": 6.404590000000098,
          "timestamp": "2025-07-08T22:25:02.315Z"
        },
        {
          "runNumber": 3,
          "processingTime": 6.154751000000033,
          "timestamp": "2025-07-08T22:25:02.331Z"
        },
        {
          "runNumber": 4,
          "processingTime": 3.1047320000000127,
          "timestamp": "2025-07-08T22:25:02.345Z"
        },
        {
          "runNumber": 5,
          "processingTime": 3.8377980000000207,
          "timestamp": "2025-07-08T22:25:02.359Z"
        },
        {
          "runNumber": 6,
          "processingTime": 3.742278999999826,
          "timestamp": "2025-07-08T22:25:02.373Z"
        },
        {
          "runNumber": 7,
          "processingTime": 2.8196560000001227,
          "timestamp": "2025-07-08T22:25:02.386Z"
        },
        {
          "runNumber": 8,
          "processingTime": 2.5382179999999153,
          "timestamp": "2025-07-08T22:25:02.399Z"
        },
        {
          "runNumber": 9,
          "processingTime": 4.099590000000035,
          "timestamp": "2025-07-08T22:25:02.413Z"
        },
        {
          "runNumber": 10,
          "processingTime": 3.8162180000001626,
          "timestamp": "2025-07-08T22:25:02.427Z"
        }
      ]
    },
    {
      "name": "Large text content processing",
      "averageTime": 1.982628749999975,
      "minTime": 1.482183999999961,
      "maxTime": 2.6767680000000382,
      "standardDeviation": 0.3880951417177863,
      "coefficient": 19.57477625187223,
      "threshold": 50,
      "status": "PASS",
      "category": "processing",
      "description": "Text processing should be faster than HTML",
      "dataSize": "123.3KB",
      "details": "Processing 123.3KB of plain text with 19000 words",
      "score": 4,
      "reliability": "LOW",
      "runs": [
        {
          "runNumber": 1,
          "processingTime": 2.6767680000000382,
          "timestamp": "2025-07-08T22:25:02.444Z"
        },
        {
          "runNumber": 2,
          "processingTime": 1.4416989999999714,
          "timestamp": "2025-07-08T22:25:02.456Z"
        },
        {
          "runNumber": 3,
          "processingTime": 2.115342999999939,
          "timestamp": "2025-07-08T22:25:02.468Z"
        },
        {
          "runNumber": 4,
          "processingTime": 2.2592529999999442,
          "timestamp": "2025-07-08T22:25:02.481Z"
        },
        {
          "runNumber": 5,
          "processingTime": 1.6566820000000462,
          "timestamp": "2025-07-08T22:25:02.493Z"
        },
        {
          "runNumber": 6,
          "processingTime": 1.775564999999915,
          "timestamp": "2025-07-08T22:25:02.505Z"
        },
        {
          "runNumber": 7,
          "processingTime": 2.2844900000000052,
          "timestamp": "2025-07-08T22:25:02.518Z"
        },
        {
          "runNumber": 8,
          "processingTime": 2.7209009999999125,
          "timestamp": "2025-07-08T22:25:02.531Z"
        },
        {
          "runNumber": 9,
          "processingTime": 1.6107449999999517,
          "timestamp": "2025-07-08T22:25:02.543Z"
        },
        {
          "runNumber": 10,
          "processingTime": 1.482183999999961,
          "timestamp": "2025-07-08T22:25:02.555Z"
        }
      ]
    },
    {
      "name": "Multiple re-renders (10 toggles)",
      "averageTime": 1.196378500000037,
      "minTime": 0.8944300000000567,
      "maxTime": 1.500108000000182,
      "standardDeviation": 0.21589851436730503,
      "coefficient": 18.046004200785816,
      "threshold": 200,
      "status": "PASS",
      "category": "reactivity",
      "description": "Multiple state changes should be efficient",
      "dataSize": "4.0KB",
      "details": "Testing reactivity with 4.0KB content through 10 state toggles",
      "score": 1,
      "reliability": "LOW",
      "runs": [
        {
          "runNumber": 1,
          "processingTime": 3.1699140000000625,
          "timestamp": "2025-07-08T22:25:02.575Z"
        },
        {
          "runNumber": 2,
          "processingTime": 1.064429999999902,
          "timestamp": "2025-07-08T22:25:02.589Z"
        },
        {
          "runNumber": 3,
          "processingTime": 1.2049030000000585,
          "timestamp": "2025-07-08T22:25:02.602Z"
        },
        {
          "runNumber": 4,
          "processingTime": 1.327493000000004,
          "timestamp": "2025-07-08T22:25:02.615Z"
        },
        {
          "runNumber": 5,
          "processingTime": 1.1838440000001356,
          "timestamp": "2025-07-08T22:25:02.629Z"
        },
        {
          "runNumber": 6,
          "processingTime": 0.8923059999999623,
          "timestamp": "2025-07-08T22:25:02.643Z"
        },
        {
          "runNumber": 7,
          "processingTime": 1.500108000000182,
          "timestamp": "2025-07-08T22:25:02.657Z"
        },
        {
          "runNumber": 8,
          "processingTime": 0.9198480000000018,
          "timestamp": "2025-07-08T22:25:02.672Z"
        },
        {
          "runNumber": 9,
          "processingTime": 1.475971999999956,
          "timestamp": "2025-07-08T22:25:02.685Z"
        },
        {
          "runNumber": 10,
          "processingTime": 0.8944300000000567,
          "timestamp": "2025-07-08T22:25:02.699Z"
        }
      ]
    },
    {
      "name": "Computed properties reactivity",
      "averageTime": 1.5972213750000037,
      "minTime": 1.1932309999999688,
      "maxTime": 2.050952000000052,
      "standardDeviation": 0.31076005596357253,
      "coefficient": 19.45629208496986,
      "threshold": 100,
      "status": "PASS",
      "category": "reactivity",
      "description": "Reactive property updates should be fast",
      "dataSize": "6.1KB",
      "details": "Testing reactive updates with 6.1KB content across 3 property changes",
      "score": 2,
      "reliability": "LOW",
      "runs": [
        {
          "runNumber": 1,
          "processingTime": 2.790482000000111,
          "timestamp": "2025-07-08T22:25:02.716Z"
        },
        {
          "runNumber": 2,
          "processingTime": 2.050952000000052,
          "timestamp": "2025-07-08T22:25:02.732Z"
        },
        {
          "runNumber": 3,
          "processingTime": 1.3072460000000774,
          "timestamp": "2025-07-08T22:25:02.745Z"
        },
        {
          "runNumber": 4,
          "processingTime": 1.8053409999999985,
          "timestamp": "2025-07-08T22:25:02.759Z"
        },
        {
          "runNumber": 5,
          "processingTime": 1.8038480000000163,
          "timestamp": "2025-07-08T22:25:02.773Z"
        },
        {
          "runNumber": 6,
          "processingTime": 1.8774269999998978,
          "timestamp": "2025-07-08T22:25:02.788Z"
        },
        {
          "runNumber": 7,
          "processingTime": 1.2093919999999798,
          "timestamp": "2025-07-08T22:25:02.802Z"
        },
        {
          "runNumber": 8,
          "processingTime": 1.1932309999999688,
          "timestamp": "2025-07-08T22:25:02.816Z"
        },
        {
          "runNumber": 9,
          "processingTime": 1.14941900000008,
          "timestamp": "2025-07-08T22:25:02.829Z"
        },
        {
          "runNumber": 10,
          "processingTime": 1.530334000000039,
          "timestamp": "2025-07-08T22:25:02.843Z"
        }
      ]
    },
    {
      "name": "HTML sanitization overhead",
      "averageTime": 1.6679313749999949,
      "minTime": 1.2876189999999497,
      "maxTime": 2.0318059999999605,
      "standardDeviation": 0.2930597985987286,
      "coefficient": 17.570255167046636,
      "threshold": 150,
      "status": "PASS",
      "category": "sanitization",
      "description": "HTML sanitization should not significantly impact performance",
      "dataSize": "2.3KB",
      "details": "Sanitizing 2.3KB of malicious HTML with 80 dangerous elements",
      "score": 1,
      "reliability": "LOW",
      "runs": [
        {
          "runNumber": 1,
          "processingTime": 2.0318059999999605,
          "timestamp": "2025-07-08T22:25:02.858Z"
        },
        {
          "runNumber": 2,
          "processingTime": 1.9441020000001572,
          "timestamp": "2025-07-08T22:25:02.870Z"
        },
        {
          "runNumber": 3,
          "processingTime": 2.3530900000000656,
          "timestamp": "2025-07-08T22:25:02.883Z"
        },
        {
          "runNumber": 4,
          "processingTime": 1.9796579999999722,
          "timestamp": "2025-07-08T22:25:02.895Z"
        },
        {
          "runNumber": 5,
          "processingTime": 1.2876189999999497,
          "timestamp": "2025-07-08T22:25:02.906Z"
        },
        {
          "runNumber": 6,
          "processingTime": 1.0927630000001045,
          "timestamp": "2025-07-08T22:25:02.918Z"
        },
        {
          "runNumber": 7,
          "processingTime": 1.3184660000001713,
          "timestamp": "2025-07-08T22:25:02.929Z"
        },
        {
          "runNumber": 8,
          "processingTime": 1.464529999999968,
          "timestamp": "2025-07-08T22:25:02.941Z"
        },
        {
          "runNumber": 9,
          "processingTime": 1.4676959999999326,
          "timestamp": "2025-07-08T22:25:02.953Z"
        },
        {
          "runNumber": 10,
          "processingTime": 1.8495739999998477,
          "timestamp": "2025-07-08T22:25:02.965Z"
        }
      ]
    },
    {
      "name": "Memory usage (20 components)",
      "averageTime": 16.69783750000005,
      "minTime": 11.91975900000034,
      "maxTime": 25.261559000000034,
      "standardDeviation": 3.750250072151963,
      "coefficient": 22.45949556133812,
      "threshold": 500,
      "status": "PASS",
      "category": "memory",
      "description": "Creating multiple components should not cause memory issues",
      "dataSize": "4.0KB × 20",
      "details": "Created 20 components with 4.0KB each",
      "score": 3,
      "reliability": "LOW",
      "runs": [
        {
          "runNumber": 1,
          "processingTime": 26.139498000000003,
          "timestamp": "2025-07-08T22:25:03.005Z"
        },
        {
          "runNumber": 2,
          "processingTime": 16.10173400000008,
          "timestamp": "2025-07-08T22:25:03.036Z"
        },
        {
          "runNumber": 3,
          "processingTime": 14.463586999999961,
          "timestamp": "2025-07-08T22:25:03.062Z"
        },
        {
          "runNumber": 4,
          "processingTime": 14.635138999999981,
          "timestamp": "2025-07-08T22:25:03.089Z"
        },
        {
          "runNumber": 5,
          "processingTime": 25.261559000000034,
          "timestamp": "2025-07-08T22:25:03.126Z"
        },
        {
          "runNumber": 6,
          "processingTime": 18.85528599999998,
          "timestamp": "2025-07-08T22:25:03.157Z"
        },
        {
          "runNumber": 7,
          "processingTime": 17.050265999999738,
          "timestamp": "2025-07-08T22:25:03.186Z"
        },
        {
          "runNumber": 8,
          "processingTime": 15.295370000000275,
          "timestamp": "2025-07-08T22:25:03.216Z"
        },
        {
          "runNumber": 9,
          "processingTime": 11.776330000000144,
          "timestamp": "2025-07-08T22:25:03.240Z"
        },
        {
          "runNumber": 10,
          "processingTime": 11.91975900000034,
          "timestamp": "2025-07-08T22:25:03.264Z"
        }
      ]
    },
    {
      "name": "Edge case: extremely long word",
      "averageTime": 1.452481999999975,
      "minTime": 1.043550000000323,
      "maxTime": 1.8101300000002993,
      "standardDeviation": 0.24067370802293625,
      "coefficient": 16.569823792855292,
      "threshold": 50,
      "status": "PASS",
      "category": "edge-case",
      "description": "Extremely long words should be handled efficiently",
      "dataSize": "9.8KB",
      "details": "Processing 9.8KB single word (10000 characters)",
      "score": 3,
      "reliability": "LOW",
      "runs": [
        {
          "runNumber": 1,
          "processingTime": 1.8147390000003725,
          "timestamp": "2025-07-08T22:25:03.278Z"
        },
        {
          "runNumber": 2,
          "processingTime": 1.2143609999998262,
          "timestamp": "2025-07-08T22:25:03.289Z"
        },
        {
          "runNumber": 3,
          "processingTime": 1.5801479999995536,
          "timestamp": "2025-07-08T22:25:03.301Z"
        },
        {
          "runNumber": 4,
          "processingTime": 1.043550000000323,
          "timestamp": "2025-07-08T22:25:03.312Z"
        },
        {
          "runNumber": 5,
          "processingTime": 0.888028000000304,
          "timestamp": "2025-07-08T22:25:03.323Z"
        },
        {
          "runNumber": 6,
          "processingTime": 1.4307879999996658,
          "timestamp": "2025-07-08T22:25:03.335Z"
        },
        {
          "runNumber": 7,
          "processingTime": 1.8101300000002993,
          "timestamp": "2025-07-08T22:25:03.347Z"
        },
        {
          "runNumber": 8,
          "processingTime": 1.6137109999999666,
          "timestamp": "2025-07-08T22:25:03.360Z"
        },
        {
          "runNumber": 9,
          "processingTime": 1.2784609999998793,
          "timestamp": "2025-07-08T22:25:03.372Z"
        },
        {
          "runNumber": 10,
          "processingTime": 1.648707000000286,
          "timestamp": "2025-07-08T22:25:03.384Z"
        }
      ]
    },
    {
      "name": "Concurrent component creation",
      "averageTime": 8.289870875000076,
      "minTime": 6.944464000000153,
      "maxTime": 10.705999000000247,
      "standardDeviation": 1.206200709389458,
      "coefficient": 14.550295506134129,
      "threshold": 500,
      "status": "PASS",
      "category": "processing",
      "description": "Concurrent component creation should be efficient",
      "dataSize": "2.4KB × 10",
      "details": "Creating 10 components simultaneously with 2.4KB each",
      "score": 2,
      "reliability": "LOW",
      "runs": [
        {
          "runNumber": 1,
          "processingTime": 11.648107999999866,
          "timestamp": "2025-07-08T22:25:03.407Z"
        },
        {
          "runNumber": 2,
          "processingTime": 8.732542000000194,
          "timestamp": "2025-07-08T22:25:03.426Z"
        },
        {
          "runNumber": 3,
          "processingTime": 6.4736989999996695,
          "timestamp": "2025-07-08T22:25:03.442Z"
        },
        {
          "runNumber": 4,
          "processingTime": 8.082280999999966,
          "timestamp": "2025-07-08T22:25:03.461Z"
        },
        {
          "runNumber": 5,
          "processingTime": 9.256355999999869,
          "timestamp": "2025-07-08T22:25:03.480Z"
        },
        {
          "runNumber": 6,
          "processingTime": 6.99214400000028,
          "timestamp": "2025-07-08T22:25:03.498Z"
        },
        {
          "runNumber": 7,
          "processingTime": 8.376803999999993,
          "timestamp": "2025-07-08T22:25:03.516Z"
        },
        {
          "runNumber": 8,
          "processingTime": 7.2283769999999095,
          "timestamp": "2025-07-08T22:25:03.534Z"
        },
        {
          "runNumber": 9,
          "processingTime": 6.944464000000153,
          "timestamp": "2025-07-08T22:25:03.552Z"
        },
        {
          "runNumber": 10,
          "processingTime": 10.705999000000247,
          "timestamp": "2025-07-08T22:25:03.573Z"
        }
      ]
    },
    {
      "name": "Complex HTML structure",
      "averageTime": 2.550054750000129,
      "minTime": 2.118760000000293,
      "maxTime": 4.087598000000071,
      "standardDeviation": 0.592183233306753,
      "coefficient": 23.222373296366406,
      "threshold": 200,
      "status": "PASS",
      "category": "processing",
      "description": "Complex nested HTML should be processed efficiently",
      "dataSize": "12.8KB",
      "details": "Processing 12.8KB complex nested HTML with 360 tags",
      "score": 1,
      "reliability": "LOW",
      "runs": [
        {
          "runNumber": 1,
          "processingTime": 7.864972999999736,
          "timestamp": "2025-07-08T22:25:03.593Z"
        },
        {
          "runNumber": 2,
          "processingTime": 2.3738790000002155,
          "timestamp": "2025-07-08T22:25:03.605Z"
        },
        {
          "runNumber": 3,
          "processingTime": 2.3395439999999326,
          "timestamp": "2025-07-08T22:25:03.618Z"
        },
        {
          "runNumber": 4,
          "processingTime": 2.4543100000000777,
          "timestamp": "2025-07-08T22:25:03.630Z"
        },
        {
          "runNumber": 5,
          "processingTime": 2.118760000000293,
          "timestamp": "2025-07-08T22:25:03.643Z"
        },
        {
          "runNumber": 6,
          "processingTime": 2.3120120000003226,
          "timestamp": "2025-07-08T22:25:03.655Z"
        },
        {
          "runNumber": 7,
          "processingTime": 2.4982319999999163,
          "timestamp": "2025-07-08T22:25:03.668Z"
        },
        {
          "runNumber": 8,
          "processingTime": 2.216103000000203,
          "timestamp": "2025-07-08T22:25:03.680Z"
        },
        {
          "runNumber": 9,
          "processingTime": 4.087598000000071,
          "timestamp": "2025-07-08T22:25:03.694Z"
        },
        {
          "runNumber": 10,
          "processingTime": 1.9123819999999796,
          "timestamp": "2025-07-08T22:25:03.706Z"
        }
      ]
    }
  ]
}